{
  "exchange": "hyperliquid",
  "total": 34,
  "updated_at": "2026-06-22 19:15:58.128958",
  "documents_by_type": {
    "Other": [
      {
        "title": "Untitled",
        "filename": "activation-gas-fee.md",
        "path": "docs/hyperliquid/for-developers/api/activation-gas-fee.md",
        "source_url": "",
        "updated_at": "2026-06-22 19:12:42.232684"
      },
      {
        "title": "Untitled",
        "filename": "asset-ids.md",
        "path": "docs/hyperliquid/for-developers/api/asset-ids.md",
        "source_url": "",
        "updated_at": "2026-06-22 19:12:48.486131"
      },
      {
        "title": "Untitled",
        "filename": "bridge2.md",
        "path": "docs/hyperliquid/for-developers/api/bridge2.md",
        "source_url": "",
        "updated_at": "2026-06-22 19:12:54.797923"
      },
      {
        "title": "Untitled",
        "filename": "deploying-hip-1-and-hip-2-assets.md",
        "path": "docs/hyperliquid/for-developers/api/deploying-hip-1-and-hip-2-assets.md",
        "source_url": "",
        "updated_at": "2026-06-22 19:13:01.188300"
      },
      {
        "title": "Untitled",
        "filename": "error-responses.md",
        "path": "docs/hyperliquid/for-developers/api/error-responses.md",
        "source_url": "",
        "updated_at": "2026-06-22 19:13:07.492611"
      },
      {
        "title": "Untitled",
        "filename": "exchange-endpoint.md",
        "path": "docs/hyperliquid/for-developers/api/exchange-endpoint.md",
        "source_url": "",
        "updated_at": "2026-06-22 19:13:14.231812"
      },
      {
        "title": "Untitled",
        "filename": "hip-3-deployer-actions.md",
        "path": "docs/hyperliquid/for-developers/api/hip-3-deployer-actions.md",
        "source_url": "",
        "updated_at": "2026-06-22 19:13:20.580921"
      },
      {
        "title": "Untitled",
        "filename": "perpetuals.md",
        "path": "docs/hyperliquid/for-developers/api/info-endpoint/perpetuals.md",
        "source_url": "",
        "updated_at": "2026-06-22 19:13:33.872633"
      },
      {
        "title": "Untitled",
        "filename": "spot.md",
        "path": "docs/hyperliquid/for-developers/api/info-endpoint/spot.md",
        "source_url": "",
        "updated_at": "2026-06-22 19:13:40.371654"
      },
      {
        "title": "Untitled",
        "filename": "info-endpoint.md",
        "path": "docs/hyperliquid/for-developers/api/info-endpoint.md",
        "source_url": "",
        "updated_at": "2026-06-22 19:13:27.315858"
      },
      {
        "title": "Untitled",
        "filename": "nonces-and-api-wallets.md",
        "path": "docs/hyperliquid/for-developers/api/nonces-and-api-wallets.md",
        "source_url": "",
        "updated_at": "2026-06-22 19:13:46.681633"
      },
      {
        "title": "Untitled",
        "filename": "notation.md",
        "path": "docs/hyperliquid/for-developers/api/notation.md",
        "source_url": "",
        "updated_at": "2026-06-22 19:13:52.962940"
      },
      {
        "title": "Untitled",
        "filename": "optimizing-latency.md",
        "path": "docs/hyperliquid/for-developers/api/optimizing-latency.md",
        "source_url": "",
        "updated_at": "2026-06-22 19:13:59.336151"
      },
      {
        "title": "Untitled",
        "filename": "priority-fees.md",
        "path": "docs/hyperliquid/for-developers/api/priority-fees.md",
        "source_url": "",
        "updated_at": "2026-06-22 19:14:05.615630"
      },
      {
        "title": "Untitled",
        "filename": "rate-limits-and-user-limits.md",
        "path": "docs/hyperliquid/for-developers/api/rate-limits-and-user-limits.md",
        "source_url": "",
        "updated_at": "2026-06-22 19:14:11.925248"
      },
      {
        "title": "Untitled",
        "filename": "signing.md",
        "path": "docs/hyperliquid/for-developers/api/signing.md",
        "source_url": "",
        "updated_at": "2026-06-22 19:14:18.190856"
      },
      {
        "title": "Untitled",
        "filename": "tick-and-lot-size.md",
        "path": "docs/hyperliquid/for-developers/api/tick-and-lot-size.md",
        "source_url": "",
        "updated_at": "2026-06-22 19:14:24.457675"
      },
      {
        "title": "Untitled",
        "filename": "post-requests.md",
        "path": "docs/hyperliquid/for-developers/api/websocket/post-requests.md",
        "source_url": "",
        "updated_at": "2026-06-22 19:14:37.062533"
      },
      {
        "title": "Untitled",
        "filename": "subscriptions.md",
        "path": "docs/hyperliquid/for-developers/api/websocket/subscriptions.md",
        "source_url": "",
        "updated_at": "2026-06-22 19:14:43.499038"
      },
      {
        "title": "Untitled",
        "filename": "timeouts-and-heartbeats.md",
        "path": "docs/hyperliquid/for-developers/api/websocket/timeouts-and-heartbeats.md",
        "source_url": "",
        "updated_at": "2026-06-22 19:14:49.773910"
      },
      {
        "title": "Untitled",
        "filename": "websocket.md",
        "path": "docs/hyperliquid/for-developers/api/websocket.md",
        "source_url": "",
        "updated_at": "2026-06-22 19:14:30.746135"
      },
      {
        "title": "Untitled",
        "filename": "api.md",
        "path": "docs/hyperliquid/for-developers/api.md",
        "source_url": "",
        "updated_at": "2026-06-22 19:12:35.878837"
      },
      {
        "title": "Untitled",
        "filename": "dual-block-architecture.md",
        "path": "docs/hyperliquid/for-developers/hyperevm/dual-block-architecture.md",
        "source_url": "",
        "updated_at": "2026-06-22 19:15:02.292244"
      },
      {
        "title": "Untitled",
        "filename": "hypercore-less-than-greater-than-hyperevm-transfers.md",
        "path": "docs/hyperliquid/for-developers/hyperevm/hypercore-less-than-greater-than-hyperevm-transfers.md",
        "source_url": "",
        "updated_at": "2026-06-22 19:15:08.561994"
      },
      {
        "title": "Untitled",
        "filename": "interacting-with-hypercore.md",
        "path": "docs/hyperliquid/for-developers/hyperevm/interacting-with-hypercore.md",
        "source_url": "",
        "updated_at": "2026-06-22 19:15:14.910016"
      },
      {
        "title": "Untitled",
        "filename": "interaction-timings.md",
        "path": "docs/hyperliquid/for-developers/hyperevm/interaction-timings.md",
        "source_url": "",
        "updated_at": "2026-06-22 19:15:21.220031"
      },
      {
        "title": "Untitled",
        "filename": "json-rpc.md",
        "path": "docs/hyperliquid/for-developers/hyperevm/json-rpc.md",
        "source_url": "",
        "updated_at": "2026-06-22 19:15:26.500892"
      },
      {
        "title": "Untitled",
        "filename": "raw-hyperevm-block-data.md",
        "path": "docs/hyperliquid/for-developers/hyperevm/raw-hyperevm-block-data.md",
        "source_url": "",
        "updated_at": "2026-06-22 19:15:32.807747"
      },
      {
        "title": "Untitled",
        "filename": "wrapped-hype.md",
        "path": "docs/hyperliquid/for-developers/hyperevm/wrapped-hype.md",
        "source_url": "",
        "updated_at": "2026-06-22 19:15:39.153889"
      },
      {
        "title": "Untitled",
        "filename": "hyperevm.md",
        "path": "docs/hyperliquid/for-developers/hyperevm.md",
        "source_url": "",
        "updated_at": "2026-06-22 19:14:56.058943"
      },
      {
        "title": "Untitled",
        "filename": "foundation-non-validating-node.md",
        "path": "docs/hyperliquid/for-developers/nodes/foundation-non-validating-node.md",
        "source_url": "",
        "updated_at": "2026-06-22 19:15:51.768036"
      },
      {
        "title": "Untitled",
        "filename": "l1-data-schemas.md",
        "path": "docs/hyperliquid/for-developers/nodes/l1-data-schemas.md",
        "source_url": "",
        "updated_at": "2026-06-22 19:15:58.128958"
      },
      {
        "title": "Untitled",
        "filename": "nodes.md",
        "path": "docs/hyperliquid/for-developers/nodes.md",
        "source_url": "",
        "updated_at": "2026-06-22 19:15:45.469074"
      }
    ],
    "REST": [
      {
        "title": "API",
        "filename": "for-developers.md",
        "path": "docs/hyperliquid/for-developers.md",
        "source_url": "https://hyperliquid.gitbook.io/hyperliquid-docs/for-developers",
        "updated_at": "2026-06-22 19:12:29.609597"
      }
    ]
  },
  "all_documents": [
    {
      "title": "API",
      "filename": "for-developers.md",
      "path": "docs/hyperliquid/for-developers.md",
      "api_type": "REST",
      "source_url": "https://hyperliquid.gitbook.io/hyperliquid-docs/for-developers",
      "updated_at": "2026-06-22 19:12:29.609597"
    },
    {
      "title": "Untitled",
      "filename": "activation-gas-fee.md",
      "path": "docs/hyperliquid/for-developers/api/activation-gas-fee.md",
      "api_type": "Other",
      "source_url": "",
      "updated_at": "2026-06-22 19:12:42.232684"
    },
    {
      "title": "Untitled",
      "filename": "asset-ids.md",
      "path": "docs/hyperliquid/for-developers/api/asset-ids.md",
      "api_type": "Other",
      "source_url": "",
      "updated_at": "2026-06-22 19:12:48.486131"
    },
    {
      "title": "Untitled",
      "filename": "bridge2.md",
      "path": "docs/hyperliquid/for-developers/api/bridge2.md",
      "api_type": "Other",
      "source_url": "",
      "updated_at": "2026-06-22 19:12:54.797923"
    },
    {
      "title": "Untitled",
      "filename": "deploying-hip-1-and-hip-2-assets.md",
      "path": "docs/hyperliquid/for-developers/api/deploying-hip-1-and-hip-2-assets.md",
      "api_type": "Other",
      "source_url": "",
      "updated_at": "2026-06-22 19:13:01.188300"
    },
    {
      "title": "Untitled",
      "filename": "error-responses.md",
      "path": "docs/hyperliquid/for-developers/api/error-responses.md",
      "api_type": "Other",
      "source_url": "",
      "updated_at": "2026-06-22 19:13:07.492611"
    },
    {
      "title": "Untitled",
      "filename": "exchange-endpoint.md",
      "path": "docs/hyperliquid/for-developers/api/exchange-endpoint.md",
      "api_type": "Other",
      "source_url": "",
      "updated_at": "2026-06-22 19:13:14.231812"
    },
    {
      "title": "Untitled",
      "filename": "hip-3-deployer-actions.md",
      "path": "docs/hyperliquid/for-developers/api/hip-3-deployer-actions.md",
      "api_type": "Other",
      "source_url": "",
      "updated_at": "2026-06-22 19:13:20.580921"
    },
    {
      "title": "Untitled",
      "filename": "perpetuals.md",
      "path": "docs/hyperliquid/for-developers/api/info-endpoint/perpetuals.md",
      "api_type": "Other",
      "source_url": "",
      "updated_at": "2026-06-22 19:13:33.872633"
    },
    {
      "title": "Untitled",
      "filename": "spot.md",
      "path": "docs/hyperliquid/for-developers/api/info-endpoint/spot.md",
      "api_type": "Other",
      "source_url": "",
      "updated_at": "2026-06-22 19:13:40.371654"
    },
    {
      "title": "Untitled",
      "filename": "info-endpoint.md",
      "path": "docs/hyperliquid/for-developers/api/info-endpoint.md",
      "api_type": "Other",
      "source_url": "",
      "updated_at": "2026-06-22 19:13:27.315858"
    },
    {
      "title": "Untitled",
      "filename": "nonces-and-api-wallets.md",
      "path": "docs/hyperliquid/for-developers/api/nonces-and-api-wallets.md",
      "api_type": "Other",
      "source_url": "",
      "updated_at": "2026-06-22 19:13:46.681633"
    },
    {
      "title": "Untitled",
      "filename": "notation.md",
      "path": "docs/hyperliquid/for-developers/api/notation.md",
      "api_type": "Other",
      "source_url": "",
      "updated_at": "2026-06-22 19:13:52.962940"
    },
    {
      "title": "Untitled",
      "filename": "optimizing-latency.md",
      "path": "docs/hyperliquid/for-developers/api/optimizing-latency.md",
      "api_type": "Other",
      "source_url": "",
      "updated_at": "2026-06-22 19:13:59.336151"
    },
    {
      "title": "Untitled",
      "filename": "priority-fees.md",
      "path": "docs/hyperliquid/for-developers/api/priority-fees.md",
      "api_type": "Other",
      "source_url": "",
      "updated_at": "2026-06-22 19:14:05.615630"
    },
    {
      "title": "Untitled",
      "filename": "rate-limits-and-user-limits.md",
      "path": "docs/hyperliquid/for-developers/api/rate-limits-and-user-limits.md",
      "api_type": "Other",
      "source_url": "",
      "updated_at": "2026-06-22 19:14:11.925248"
    },
    {
      "title": "Untitled",
      "filename": "signing.md",
      "path": "docs/hyperliquid/for-developers/api/signing.md",
      "api_type": "Other",
      "source_url": "",
      "updated_at": "2026-06-22 19:14:18.190856"
    },
    {
      "title": "Untitled",
      "filename": "tick-and-lot-size.md",
      "path": "docs/hyperliquid/for-developers/api/tick-and-lot-size.md",
      "api_type": "Other",
      "source_url": "",
      "updated_at": "2026-06-22 19:14:24.457675"
    },
    {
      "title": "Untitled",
      "filename": "post-requests.md",
      "path": "docs/hyperliquid/for-developers/api/websocket/post-requests.md",
      "api_type": "Other",
      "source_url": "",
      "updated_at": "2026-06-22 19:14:37.062533"
    },
    {
      "title": "Untitled",
      "filename": "subscriptions.md",
      "path": "docs/hyperliquid/for-developers/api/websocket/subscriptions.md",
      "api_type": "Other",
      "source_url": "",
      "updated_at": "2026-06-22 19:14:43.499038"
    },
    {
      "title": "Untitled",
      "filename": "timeouts-and-heartbeats.md",
      "path": "docs/hyperliquid/for-developers/api/websocket/timeouts-and-heartbeats.md",
      "api_type": "Other",
      "source_url": "",
      "updated_at": "2026-06-22 19:14:49.773910"
    },
    {
      "title": "Untitled",
      "filename": "websocket.md",
      "path": "docs/hyperliquid/for-developers/api/websocket.md",
      "api_type": "Other",
      "source_url": "",
      "updated_at": "2026-06-22 19:14:30.746135"
    },
    {
      "title": "Untitled",
      "filename": "api.md",
      "path": "docs/hyperliquid/for-developers/api.md",
      "api_type": "Other",
      "source_url": "",
      "updated_at": "2026-06-22 19:12:35.878837"
    },
    {
      "title": "Untitled",
      "filename": "dual-block-architecture.md",
      "path": "docs/hyperliquid/for-developers/hyperevm/dual-block-architecture.md",
      "api_type": "Other",
      "source_url": "",
      "updated_at": "2026-06-22 19:15:02.292244"
    },
    {
      "title": "Untitled",
      "filename": "hypercore-less-than-greater-than-hyperevm-transfers.md",
      "path": "docs/hyperliquid/for-developers/hyperevm/hypercore-less-than-greater-than-hyperevm-transfers.md",
      "api_type": "Other",
      "source_url": "",
      "updated_at": "2026-06-22 19:15:08.561994"
    },
    {
      "title": "Untitled",
      "filename": "interacting-with-hypercore.md",
      "path": "docs/hyperliquid/for-developers/hyperevm/interacting-with-hypercore.md",
      "api_type": "Other",
      "source_url": "",
      "updated_at": "2026-06-22 19:15:14.910016"
    },
    {
      "title": "Untitled",
      "filename": "interaction-timings.md",
      "path": "docs/hyperliquid/for-developers/hyperevm/interaction-timings.md",
      "api_type": "Other",
      "source_url": "",
      "updated_at": "2026-06-22 19:15:21.220031"
    },
    {
      "title": "Untitled",
      "filename": "json-rpc.md",
      "path": "docs/hyperliquid/for-developers/hyperevm/json-rpc.md",
      "api_type": "Other",
      "source_url": "",
      "updated_at": "2026-06-22 19:15:26.500892"
    },
    {
      "title": "Untitled",
      "filename": "raw-hyperevm-block-data.md",
      "path": "docs/hyperliquid/for-developers/hyperevm/raw-hyperevm-block-data.md",
      "api_type": "Other",
      "source_url": "",
      "updated_at": "2026-06-22 19:15:32.807747"
    },
    {
      "title": "Untitled",
      "filename": "wrapped-hype.md",
      "path": "docs/hyperliquid/for-developers/hyperevm/wrapped-hype.md",
      "api_type": "Other",
      "source_url": "",
      "updated_at": "2026-06-22 19:15:39.153889"
    },
    {
      "title": "Untitled",
      "filename": "hyperevm.md",
      "path": "docs/hyperliquid/for-developers/hyperevm.md",
      "api_type": "Other",
      "source_url": "",
      "updated_at": "2026-06-22 19:14:56.058943"
    },
    {
      "title": "Untitled",
      "filename": "foundation-non-validating-node.md",
      "path": "docs/hyperliquid/for-developers/nodes/foundation-non-validating-node.md",
      "api_type": "Other",
      "source_url": "",
      "updated_at": "2026-06-22 19:15:51.768036"
    },
    {
      "title": "Untitled",
      "filename": "l1-data-schemas.md",
      "path": "docs/hyperliquid/for-developers/nodes/l1-data-schemas.md",
      "api_type": "Other",
      "source_url": "",
      "updated_at": "2026-06-22 19:15:58.128958"
    },
    {
      "title": "Untitled",
      "filename": "nodes.md",
      "path": "docs/hyperliquid/for-developers/nodes.md",
      "api_type": "Other",
      "source_url": "",
      "updated_at": "2026-06-22 19:15:45.469074"
    }
  ]
}